{
  "$schema": "https://biomejs.dev/schemas/1.9.4/schema.json",
  "vcs": {
    "enabled": true,
    "clientKind": "git",
    "useIgnoreFile": true
  },
  "files": {
    "ignoreUnknown": true,
    "ignore": []
  },
  "formatter": {
    "enabled": true,
    "indentStyle": "space",
    "useEditorconfig": true
  },
  "organizeImports": {
    "enabled": false
  },
  "linter": {
    "enabled": true,
    "rules": {
      "recommended": true
    }
  },
  "javascript": {
    "formatter": {
      "attributePosition": "multiline"
    }
  },
  "json": {
    "parser": {
      "allowComments": true
    }
  }
}
